bin/llava-cli
bin/convert.py
bin/convert-lora-to-ggml.py
llama_cpp_python_cross.libs/libllama-63cac66b.so
llama_cpp_python_cross.libs/libopenblas-r0-e9c9f581.3.15.so
llama_cpp_python_cross.libs/libgfortran-45ab12a8.so.5.0.0
llama_cpp_python_cross-0.2.60.dist-info/METADATA
llama_cpp_python_cross-0.2.60.dist-info/WHEEL
llama_cpp_python_cross-0.2.60.dist-info/entry_points.txt
llama_cpp_python_cross-0.2.60.dist-info/RECORD
llama_cpp_python_cross-0.2.60.dist-info/licenses/LICENSE.md
llama_cpp/libllava.so
llama_cpp/_logger.py
llama_cpp/llama_speculative.py
llama_cpp/llama_grammar.py
llama_cpp/llama_cache.py
llama_cpp/llama.py
llama_cpp/llama_cpp.py
llama_cpp/__init__.py
llama_cpp/_internals.py
llama_cpp/llama_tokenizer.py
llama_cpp/py.typed
llama_cpp/_utils.py
llama_cpp/llama_chat_format.py
llama_cpp/llama_types.py
llama_cpp/llava_cpp.py
llama_cpp/libllama.so
llama_cpp/server/settings.py
llama_cpp/server/types.py
llama_cpp/server/app.py
llama_cpp/server/model.py
llama_cpp/server/errors.py
llama_cpp/server/__init__.py
llama_cpp/server/cli.py
llama_cpp/server/__main__.py
include/ggml-alloc.h
include/ggml.h
include/ggml-backend.h
include/llama.h
lib/libggml_shared.so
lib64/libllava.so
lib64/libllama.so
lib64/cmake/Llama/LlamaConfig.cmake
lib64/cmake/Llama/LlamaConfigVersion.cmake
