Metadata-Version: 2.1
Name: llama_cpp_python-cross
Version: 0.2.60
Summary: Python bindings for the llama.cpp library
Author-Email: Andrei Betlen <abetlen@gmail.com>
License: MIT
Classifier: Programming Language :: Python :: 3
Classifier: Programming Language :: Python :: 3.8
Classifier: Programming Language :: Python :: 3.9
Classifier: Programming Language :: Python :: 3.10
Classifier: Programming Language :: Python :: 3.11
Classifier: Programming Language :: Python :: 3.12
Project-URL: Homepage, https://github.com/abetlen/llama-cpp-python
Project-URL: Issues, https://github.com/abetlen/llama-cpp-python/issues
Project-URL: Documentation, https://llama-cpp-python.readthedocs.io/en/latest/
Project-URL: Changelog, https://llama-cpp-python.readthedocs.io/en/latest/changelog/
Requires-Python: >=3.8
Requires-Dist: typing-extensions>=4.5.0
Requires-Dist: numpy>=1.20.0
Requires-Dist: diskcache>=5.6.1
Requires-Dist: jinja2>=2.11.3
Requires-Dist: uvicorn>=0.22.0; extra == "server"
Requires-Dist: fastapi>=0.100.0; extra == "server"
Requires-Dist: pydantic-settings>=2.0.1; extra == "server"
Requires-Dist: sse-starlette>=1.6.1; extra == "server"
Requires-Dist: starlette-context<0.4,>=0.3.6; extra == "server"
Requires-Dist: pytest>=7.4.0; extra == "test"
Requires-Dist: httpx>=0.24.1; extra == "test"
Requires-Dist: scipy>=1.10; extra == "test"
Requires-Dist: black>=23.3.0; extra == "dev"
Requires-Dist: twine>=4.0.2; extra == "dev"
Requires-Dist: mkdocs>=1.4.3; extra == "dev"
Requires-Dist: mkdocstrings[python]>=0.22.0; extra == "dev"
Requires-Dist: mkdocs-material>=9.1.18; extra == "dev"
Requires-Dist: pytest>=7.4.0; extra == "dev"
Requires-Dist: httpx>=0.24.1; extra == "dev"
Requires-Dist: llama_cpp_python[dev,server,test]; extra == "all"
Provides-Extra: server
Provides-Extra: test
Provides-Extra: dev
Provides-Extra: all
License-File: LICENSE.md
